upsetty/__init__.py
upsetty/demo.py
upsetty/plotting.py
upsetty/set_association.py
upsetty/upset.py
upsetty/utils.py
upsetty-0.1.3.dist-info/LICENSE
upsetty-0.1.3.dist-info/METADATA
upsetty-0.1.3.dist-info/WHEEL
upsetty-0.1.3.dist-info/top_level.txt
upsetty-0.1.3.dist-info/RECORD
