Metadata-Version: 2.1
Name: upsetty
Version: 0.1.3
Summary: An UpSet plot creation package using Plotly
Home-page: https://github.com/eskin22/upsetty
Download-URL: https://pypi.org/project/upsetty/
Author: eskin22
Author-email: blakepmcbride@gmail.com
License: MIT
Keywords: upset,upset-plot,upsetplot,set-interaction,set-intersection,set-interactions,sets,plotting,visualization,data-visualization,visualization-tools,data-visualization-tools,python,python3,python310,pandas,plotly
Classifier: Development Status :: 3 - Alpha
Classifier: License :: OSI Approved :: MIT License
Classifier: Intended Audience :: Developers
Classifier: Programming Language :: Python :: 3
Classifier: Programming Language :: Python :: 3.10
Classifier: Topic :: Software Development :: Build Tools
Classifier: Topic :: Software Development :: Libraries :: Python Modules
Classifier: Topic :: Utilities
Classifier: Topic :: Scientific/Engineering :: Visualization
License-File: LICENSE
Requires-Dist: plotly
Requires-Dist: pandas
Requires-Dist: numpy
